tests/main/test_parserless_apitest_ascend_like.py
tests/main/test_imc/__init__.py
tests/main/test_imc/test_aimc.py
tests/main/test_imc/test_dimc.py
tests/main/test_origin/test_ascend_like.py
tests/main/test_origin/test_edge_tpu_like.py
tests/main/test_origin/test_gemm_l1.py
tests/main/test_origin/test_gemm_l1_l3.py
tests/main/test_origin/test_meta_prototype_like.py
tests/main/test_origin/test_tesla_npu_like.py
tests/main/test_origin/test_tpu_like.py
tests/main/test_with_exploit_data_locality/__init__.py
tests/main/test_with_exploit_data_locality/test_ascend_like.py
tests/main/test_with_exploit_data_locality/test_edge_tpu_like.py
tests/main/test_with_exploit_data_locality/test_meta_prototype_like.py
tests/main/test_with_exploit_data_locality/test_tesla_npu_like.py
tests/main/test_with_exploit_data_locality/test_tpu_like.py
tests/main/test_with_mix_spatial_mapping/__init__.py
tests/main/test_with_mix_spatial_mapping/test_ascend_like.py
tests/main/test_with_mix_spatial_mapping/test_edge_tpu_like.py
tests/main/test_with_mix_spatial_mapping/test_meta_prototype_like.py
tests/main/test_with_mix_spatial_mapping/test_tesla_npu_like.py
tests/main/test_with_mix_spatial_mapping/test_tpu_like.py
zigzag/__init__.py
zigzag/__main__.py
zigzag/api.py
zigzag/datatypes.py
zigzag/py.typed
zigzag/utils.py
zigzag/cacti/README.md
zigzag/cacti/cacti_parser.py
zigzag/cacti/__pycache__/cacti_parser.cpython-311.opt-typeguard421.pyc
zigzag/cacti/__pycache__/cacti_parser.cpython-311.pyc
zigzag/cacti/cacti_master/2DDRAM_Samsung2GbDDR2.cfg
zigzag/cacti/cacti_master/2DDRAM_micron1Gb.cfg
zigzag/cacti/cacti_master/3DDRAM_Samsung3D8Gb_extened.cfg
zigzag/cacti/cacti_master/README
zigzag/cacti/cacti_master/TSV.cc
zigzag/cacti/cacti_master/TSV.h
zigzag/cacti/cacti_master/Ucache.cc
zigzag/cacti/cacti_master/Ucache.h
zigzag/cacti/cacti_master/arbiter.cc
zigzag/cacti/cacti_master/arbiter.h
zigzag/cacti/cacti_master/area.cc
zigzag/cacti/cacti_master/area.h
zigzag/cacti/cacti_master/bank.cc
zigzag_dse-3.8.5.dist-info/licenses/LICENSE
zigzag_dse-3.8.5.dist-info/METADATA
zigzag_dse-3.8.5.dist-info/WHEEL
zigzag_dse-3.8.5.dist-info/entry_points.txt
zigzag_dse-3.8.5.dist-info/top_level.txt
zigzag_dse-3.8.5.dist-info/RECORD
