Metadata-Version: 2.3
Name: zigzag-dse
Version: 3.8.5
Summary: ZigZag - Deep Learning Hardware Design Space Exploration
Author-email: Arne Symons <arne.symons@kuleuven.be>, Linyan Mei <linyan.mei@kuleuven.be>
License: MIT
Project-URL: Homepage, https://github.com/KULeuven-MICAS/zigzag
Keywords: zigzag,dse,design-space-exploration,machine-learning,deep-learning,mapping
Classifier: Programming Language :: Python
Requires-Python: >=3.11
Requires-Dist: numpy
Requires-Dist: networkx
Requires-Dist: sympy
Requires-Dist: matplotlib
Requires-Dist: onnx
Requires-Dist: tqdm
Requires-Dist: multiprocessing_on_dill
Requires-Dist: pyyaml
Requires-Dist: cerberus
Requires-Dist: seaborn
Requires-Dist: typeguard
Provides-Extra: dev
Requires-Dist: bumpver; extra == "dev"
Requires-Dist: pip-tools; extra == "dev"
Requires-Dist: build; extra == "dev"
Requires-Dist: twine; extra == "dev"
Requires-Dist: pytest; extra == "dev"
Requires-Dist: pre-commit; extra == "dev"
Dynamic: license-file
